{
  "slug": "upper-karnali",
  "entries": [
    {
      "commons_title": "File:Deuti Bajai Hindu Temple of Surkhet,Nepal.jpg",
      "src": "upper-karnali/deuti-bajai-hindu-temple-of-surkhet-nepal.jpg",
      "filename": "deuti-bajai-hindu-temple-of-surkhet-nepal.jpg",
      "caption": "The Gangamala Deuti Bajai Temple, located in Pipira of Birendranagar Municipality, Surkhet District, is a major religious tourist destination not only in Surkhet District but al…",
      "credit": "Sandesh Giri",
      "license": "CC BY-SA 4.0",
      "license_url": "https://creativecommons.org/licenses/by-sa/4.0",
      "source_url": "https://commons.wikimedia.org/wiki/File%3ADeuti_Bajai_Hindu_Temple_of_Surkhet%2CNepal.jpg",
      "width": 3555,
      "height": 2666,
      "fetched_at": 1776662656
    },
    {
      "commons_title": "File:Nepal Tribeni Trek.jpg",
      "src": "upper-karnali/nepal-tribeni-trek.jpg",
      "filename": "nepal-tribeni-trek.jpg",
      "caption": "Nepal has a full of hidden trekking trails which take you close to the gorgeous and nature surrounding of Nepal.",
      "credit": "Dipak Nishchal",
      "license": "CC BY-SA 4.0",
      "license_url": "https://creativecommons.org/licenses/by-sa/4.0",
      "source_url": "https://commons.wikimedia.org/wiki/File%3ANepal_Tribeni_Trek.jpg",
      "width": 6000,
      "height": 4000,
      "fetched_at": 1776662657
    },
    {
      "commons_title": "File:Tribeni Trek.jpg",
      "src": "upper-karnali/tribeni-trek.jpg",
      "filename": "tribeni-trek.jpg",
      "caption": "Nepal has a full of hidden trekking trails which take you close to the gorgeous and nature surrounding of Nepal.",
      "credit": "Dipak Nishchal",
      "license": "CC BY-SA 4.0",
      "license_url": "https://creativecommons.org/licenses/by-sa/4.0",
      "source_url": "https://commons.wikimedia.org/wiki/File%3ATribeni_Trek.jpg",
      "width": 6000,
      "height": 4000,
      "fetched_at": 1776662658
    }
  ]
}